<?xml version='1.0'?>
<mission>
	<explanation>
		<page type="statement">
			Parab&#233;ns !!! Agora est&#225;s noutro patamar. J&#225; consegues
			perguntar ao cliente o que deseja comer e
			<br />
			beber. Mas temos que ser mais delicados ao falar com os clientes. A
			partir de agora vais perguntar
			<br />
			se tem sede, para depois perguntar o que deseja beber.
		</page>
		<page type="statement">
			Vamos usar um novo bloco de comando "se ... ent&#227;o ...",
			tamb&#233;m chamado bloco condicional. Ent&#227;o
			<br />
			vais perguntar ao cliente se tem sede, para depois perguntares o que
			deseja beber e ir buscar a bebida.
		</page>
		<page type="statement">
			Atende os tr&#234;s clientes perguntando se t&#234;m sede e traz as
			suas bebidas.
			<br />
			<br />
			Aten&#231;&#227;o: nem todos eles t&#234;m sede.
		</page>
		<page type="hint" origin="command" id="1" dir="up">
			Nesse menu
			est&#227;o dispon&#237;veis todos os blocos necess&#225;rios
			para
			construir um bloco de condicionais.
		</page>
		<page type="hint" origin="code" id="1" dir="up">
			Ao selecionar um bloco podes utilizar as teclas Ctr+C e Ctrl+V para
			duplicar um bloco. Selecionando obloco condicional, vais copiar esse bloco e todos os outros blocos
			dentro dele. Resolve primeiro para	um cliente e depois utiliza esse recurso para reaproveitar o
			c&#243;digo para outro cliente.
		</page>
	</explanation>
	<commands>
		<category name="snackMan" show="true" />

		<category name="goToBarCounter" show="true" />
		<category name="askForFood" show="true" />
		<category name="goToDisplay" show="true" />
		<category name="catchFood" show="true" />

		<category name="askForDrink" show="true" />
		<category name="goToCooler" show="true" />
		<category name="catchDrink" show="true" />
		<category name="askHasThirsty" show="true" />

		<category name="deliver" show="true" />

		<category name="vars" show="true" />
		<category name="logic" show="true" />

	</commands>
	<cooker>initial</cooker>
	<customersSN>
		<randomization qtd="2">thirsty</randomization>
	</customersSN>
	<customers>
		<customer>
			<id>01</id>
			<init>counter1</init>
			<dest>counter1</dest>
			<foods>
			</foods>
			<drinks>
				<drink qt="1" price="0">coke</drink>
			</drinks>
		</customer>
		<customer>
			<id>02</id>
			<init>counter2</init>
			<dest>counter2</dest>
			<foods>
			</foods>
			<drinks>
				<drink qt="1" price="0">coke</drink>
			</drinks>
		</customer>
		<customer>
			<id>03</id>
			<init>counter3</init>
			<dest>counter3</dest>
			<foods>
			</foods>
			<drinks>
				<drink qt="1" price="0">coke</drink>
			</drinks>
		</customer>
	</customers>
	<objectives ordered="false" reward="15">
		<objective pos="1" place="counter">deliver</objective>
		<objective pos="2" place="counter">deliver</objective>
		<objective pos="3" place="counter">deliver</objective>
	</objectives>
	<xml>
		<block type="controls_if" x="300" y="1" id="1">
			<value name="IF0">
				<block type="ask_askHasThirsty"></block>
			</value>
			<statement name="DO0">
				<block type="variables_set" inline="true">
					<field name="VAR">bebida</field>
					<value name="VALUE">
						<block type="ask_askForDrink"></block>
					</value>
				</block>
			</statement>
		</block>
	</xml>
</mission>

